{
  "55213": [
    [
      0.7998375711143616,
      "image_024"
    ],
    [
      0.5461702717915433,
      "image_136"
    ],
    [
      0.5073319872708862,
      "flipped_image_064"
    ],
    [
      0.48689673313043286,
      "flipped_image_072"
    ],
    [
      0.4558010175278542,
      "flipped_image_061"
    ]
  ],
  "55232": [
    [
      0.8288942480608829,
      "flipped_image_058"
    ],
    [
      0.4395909751978053,
      "flipped_image_028"
    ],
    [
      0.42835255059828375,
      "flipped_image_101"
    ],
    [
      0.42538193697865445,
      "flipped_image_113"
    ],
    [
      0.4219806663189177,
      "image_022"
    ]
  ],
  "55300": [
    [
      0.5409666875874852,
      "image_070"
    ],
    [
      0.5386034333453389,
      "flipped_image_066"
    ],
    [
      0.5306330962998517,
      "image_006"
    ],
    [
      0.5254145256522974,
      "image_095"
    ],
    [
      0.430122624585653,
      "image_085"
    ]
  ],
  "55070": [
    [
      0.5615326444108809,
      "image_093"
    ],
    [
      0.5292920981811433,
      "flipped_image_038"
    ],
    [
      0.45771161277440775,
      "flipped_image_120"
    ],
    [
      0.41723359529170034,
      "image_122"
    ],
    [
      0.41592438365713763,
      "flipped_image_028"
    ]
  ],
  "55038": [
    [
      0.8370149228478443,
      "image_018"
    ],
    [
      0.5347819756569738,
      "flipped_image_052"
    ],
    [
      0.49023838112587304,
      "image_144"
    ],
    [
      0.49011643496313384,
      "image_009"
    ],
    [
      0.4325072377470831,
      "flipped_image_148"
    ]
  ],
  "55030": [
    [
      0.5089122438030839,
      "flipped_image_003"
    ],
    [
      0.44893009640104503,
      "image_003"
    ],
    [
      0.44535477317512845,
      "flipped_image_019"
    ],
    [
      0.40695677949542214,
      "flipped_image_023"
    ],
    [
      0.3979895260669271,
      "image_113"
    ]
  ],
  "55241": [
    [
      0.5443593094426926,
      "flipped_image_016"
    ],
    [
      0.521049885836292,
      "image_135"
    ],
    [
      0.5201109725597354,
      "flipped_image_034"
    ],
    [
      0.5118384524812055,
      "image_040"
    ],
    [
      0.45311685074156205,
      "image_042"
    ]
  ],
  "55164": [
    [
      0.5022962259281109,
      "image_002"
    ],
    [
      0.49819705260260416,
      "image_049"
    ],
    [
      0.4937646576026009,
      "image_140"
    ],
    [
      0.48944051735281585,
      "image_062"
    ],
    [
      0.4521790448331085,
      "image_073"
    ]
  ],
  "55043": [
    [
      0.5534971213444783,
      "image_028"
    ],
    [
      0.5018864230107111,
      "flipped_image_064"
    ],
    [
      0.498744814361849,
      "image_015"
    ],
    [
      0.4715919871451429,
      "flipped_image_040"
    ],
    [
      0.47104025172731,
      "image_014"
    ]
  ],
  "56924": [
    [
      0.5451124330914896,
      "image_133"
    ],
    [
      0.5173118831003474,
      "flipped_image_020"
    ],
    [
      0.4985292123748414,
      "image_004"
    ],
    [
      0.4403858663950455,
      "image_092"
    ],
    [
      0.4026340540920936,
      "image_065"
    ]
  ],
  "56454": [
    [
      0.45238041579509813,
      "flipped_image_041"
    ],
    [
      0.44252495498610667,
      "image_077"
    ],
    [
      0.43223538301479153,
      "flipped_image_126"
    ],
    [
      0.42522252991433307,
      "flipped_image_039"
    ],
    [
      0.4171204049295423,
      "flipped_image_146"
    ]
  ],
  "55531": [
    [
      0.5393970585171607,
      "flipped_image_014"
    ],
    [
      0.5095912760847333,
      "image_040"
    ],
    [
      0.49797396632248236,
      "image_029"
    ],
    [
      0.4534481343848998,
      "image_139"
    ],
    [
      0.43149672727278826,
      "image_061"
    ]
  ],
  "55221": [
    [
      0.548718462634245,
      "image_093"
    ],
    [
      0.48804907799021424,
      "flipped_image_059"
    ],
    [
      0.44097801904657263,
      "flipped_image_031"
    ],
    [
      0.4096385648987126,
      "image_139"
    ],
    [
      0.4093575907024829,
      "image_132"
    ]
  ],
  "55176": [
    [
      0.5511403847593299,
      "flipped_image_127"
    ],
    [
      0.42882617755894203,
      "flipped_image_005"
    ],
    [
      0.4065722561346086,
      "image_146"
    ],
    [
      0.39671802248781307,
      "image_013"
    ],
    [
      0.3961008298391678,
      "flipped_image_117"
    ]
  ],
  "56938": [
    [
      0.5081755548036568,
      "flipped_image_076"
    ],
    [
      0.49414503785956027,
      "image_141"
    ],
    [
      0.4204006221712423,
      "flipped_image_001"
    ],
    [
      0.4115183712949925,
      "image_081"
    ],
    [
      0.4099192657778655,
      "flipped_image_077"
    ]
  ],
  "56401": [
    [
      0.5228017108773485,
      "flipped_image_028"
    ],
    [
      0.4996388182670698,
      "image_098"
    ],
    [
      0.49652322985726216,
      "image_060"
    ],
    [
      0.4535863508902275,
      "flipped_image_040"
    ],
    [
      0.4496040817691612,
      "image_076"
    ]
  ],
  "55436": [
    [
      0.47676463244195777,
      "flipped_image_025"
    ],
    [
      0.4663235894970006,
      "flipped_image_139"
    ],
    [
      0.42011730335817415,
      "flipped_image_023"
    ],
    [
      0.41708040666527313,
      "image_118"
    ],
    [
      0.4156578478449143,
      "flipped_image_035"
    ]
  ],
  "56990": [
    [
      0.475868356467658,
      "image_138"
    ],
    [
      0.4248045371701542,
      "flipped_image_003"
    ],
    [
      0.4240848593934442,
      "image_001"
    ],
    [
      0.42118961770320185,
      "flipped_image_001"
    ],
    [
      0.4016802873886915,
      "image_086"
    ]
  ],
  "55116": [
    [
      0.5360269552978397,
      "image_041"
    ],
    [
      0.528995532835556,
      "image_052"
    ],
    [
      0.5106254750092117,
      "flipped_image_035"
    ],
    [
      0.5002206219460863,
      "image_091"
    ],
    [
      0.49629900867582416,
      "image_124"
    ]
  ],
  "55453": [
    [
      0.5357669854858433,
      "flipped_image_056"
    ],
    [
      0.5274903834299653,
      "flipped_image_066"
    ],
    [
      0.5031536404299065,
      "image_070"
    ],
    [
      0.4904154610060396,
      "image_073"
    ],
    [
      0.4279857021228221,
      "flipped_image_008"
    ]
  ],
  "55119": [
    [
      0.571098897198906,
      "image_103"
    ],
    [
      0.5614744431597063,
      "image_108"
    ],
    [
      0.513136738592004,
      "flipped_image_063"
    ],
    [
      0.47828217484669033,
      "flipped_image_089"
    ],
    [
      0.43780218721106423,
      "image_028"
    ]
  ],
  "56153": [
    [
      0.5118066005075246,
      "flipped_image_136"
    ],
    [
      0.4978726844116836,
      "flipped_image_093"
    ],
    [
      0.4793622259768943,
      "flipped_image_038"
    ],
    [
      0.4724601928582371,
      "flipped_image_037"
    ],
    [
      0.4597069868987672,
      "flipped_image_003"
    ]
  ],
  "55448": [
    [
      0.5533501342984307,
      "image_127"
    ],
    [
      0.5338300102780841,
      "image_018"
    ],
    [
      0.5301501223444126,
      "flipped_image_005"
    ],
    [
      0.5150765299364348,
      "image_129"
    ],
    [
      0.480686883030053,
      "flipped_image_049"
    ]
  ],
  "55191": [
    [
      0.5407490534982421,
      "image_059"
    ],
    [
      0.5244246761050839,
      "flipped_image_041"
    ],
    [
      0.512317859418139,
      "flipped_image_104"
    ],
    [
      0.49550394918893487,
      "image_129"
    ],
    [
      0.4853601423893123,
      "flipped_image_027"
    ]
  ],
  "56623": [
    [
      0.9046050818215222,
      "image_049"
    ],
    [
      0.515564935097577,
      "flipped_image_016"
    ],
    [
      0.4216634257624168,
      "image_146"
    ],
    [
      0.41219025283200184,
      "flipped_image_110"
    ],
    [
      0.4079316123379829,
      "flipped_image_011"
    ]
  ],
  "55049": [
    [
      0.4886278830507872,
      "flipped_image_089"
    ],
    [
      0.4772212543119111,
      "flipped_image_008"
    ],
    [
      0.47435088775425044,
      "image_028"
    ],
    [
      0.43202965262383,
      "flipped_image_102"
    ],
    [
      0.4128186858224379,
      "image_145"
    ]
  ],
  "55099": [
    [
      0.5382765372169283,
      "flipped_image_106"
    ],
    [
      0.530835630859123,
      "flipped_image_104"
    ],
    [
      0.48885502471128883,
      "image_004"
    ],
    [
      0.4287985676063311,
      "flipped_image_024"
    ],
    [
      0.42083852511536324,
      "image_137"
    ]
  ],
  "55553": [
    [
      0.948331959009388,
      "flipped_image_104"
    ],
    [
      0.5387247086112588,
      "image_006"
    ],
    [
      0.521428786492556,
      "image_017"
    ],
    [
      0.5114180602163378,
      "image_133"
    ],
    [
      0.48343738101594586,
      "image_141"
    ]
  ],
  "55446": [
    [
      0.5149166622761646,
      "flipped_image_120"
    ],
    [
      0.4855432079294878,
      "image_139"
    ],
    [
      0.45588838492565015,
      "image_136"
    ],
    [
      0.44610563570610445,
      "flipped_image_140"
    ],
    [
      0.4172369781988337,
      "image_114"
    ]
  ],
  "56467": [
    [
      0.4920426085435007,
      "image_011"
    ],
    [
      0.4583202433002963,
      "flipped_image_033"
    ],
    [
      0.4152238820059,
      "flipped_image_088"
    ],
    [
      0.41493820966911077,
      "image_084"
    ],
    [
      0.40446626174805983,
      "flipped_image_022"
    ]
  ],
  "55259": [
    [
      0.5597834356937932,
      "image_004"
    ],
    [
      0.5483225005155689,
      "image_032"
    ],
    [
      0.500184767638767,
      "image_092"
    ],
    [
      0.4999245909535213,
      "flipped_image_004"
    ],
    [
      0.4643619933986072,
      "flipped_image_049"
    ]
  ],
  "55014": [
    [
      0.5297913022000172,
      "image_129"
    ],
    [
      0.47808831038665145,
      "image_006"
    ],
    [
      0.4572274173517761,
      "image_033"
    ],
    [
      0.4550076582087327,
      "flipped_image_003"
    ],
    [
      0.40492862275708774,
      "flipped_image_092"
    ]
  ],
  "56026": [
    [
      0.7775994944147119,
      "flipped_image_045"
    ],
    [
      0.4811611278197531,
      "flipped_image_127"
    ],
    [
      0.4694586767795689,
      "image_003"
    ],
    [
      0.4643131689622744,
      "flipped_image_071"
    ],
    [
      0.4162206902528935,
      "flipped_image_118"
    ]
  ],
  "55375": [
    [
      0.5312920479288001,
      "image_039"
    ],
    [
      0.49915330676706127,
      "image_038"
    ],
    [
      0.4823464806006353,
      "image_003"
    ],
    [
      0.4689775619854222,
      "image_140"
    ],
    [
      0.43865800900675816,
      "image_008"
    ]
  ],
  "55884": [
    [
      0.5382490513004496,
      "flipped_image_144"
    ],
    [
      0.5373798553632884,
      "flipped_image_142"
    ],
    [
      0.529547932608526,
      "flipped_image_037"
    ],
    [
      0.5293142892449008,
      "flipped_image_021"
    ],
    [
      0.5089863911498247,
      "image_103"
    ]
  ],
  "55463": [
    [
      0.5488997329566306,
      "image_051"
    ],
    [
      0.5331490019966691,
      "image_012"
    ],
    [
      0.5236571556019414,
      "flipped_image_024"
    ],
    [
      0.507138597447204,
      "flipped_image_073"
    ],
    [
      0.483211729745028,
      "flipped_image_039"
    ]
  ],
  "55066": [
    [
      0.5671279942882596,
      "image_059"
    ],
    [
      0.561451219969108,
      "image_037"
    ],
    [
      0.5542360706084232,
      "image_095"
    ],
    [
      0.49448481255096227,
      "flipped_image_097"
    ],
    [
      0.45159249326895773,
      "image_026"
    ]
  ],
  "55293": [
    [
      0.5218714412999852,
      "flipped_image_025"
    ],
    [
      0.507337654465051,
      "flipped_image_030"
    ],
    [
      0.44617122262270464,
      "image_129"
    ],
    [
      0.44496925270693644,
      "flipped_image_136"
    ],
    [
      0.44468646559595487,
      "flipped_image_007"
    ]
  ],
  "55447": [
    [
      0.47061043403486685,
      "image_131"
    ],
    [
      0.4588074928981588,
      "flipped_image_027"
    ],
    [
      0.4285116409064951,
      "image_101"
    ],
    [
      0.4197058691340439,
      "flipped_image_118"
    ],
    [
      0.4089083644229785,
      "flipped_image_137"
    ]
  ],
  "55549": [
    [
      0.5589360730861943,
      "flipped_image_028"
    ],
    [
      0.5460959081332964,
      "flipped_image_136"
    ],
    [
      0.4716505072249349,
      "image_008"
    ],
    [
      0.4681044086650258,
      "image_072"
    ],
    [
      0.43903441507255847,
      "image_021"
    ]
  ],
  "56658": [
    [
      0.5407632738844182,
      "flipped_image_135"
    ],
    [
      0.5383798312583842,
      "image_077"
    ],
    [
      0.5379203013642979,
      "image_135"
    ],
    [
      0.4746803289571677,
      "image_008"
    ],
    [
      0.40261560349212305,
      "image_065"
    ]
  ],
  "56792": [
    [
      0.5267555796422654,
      "flipped_image_136"
    ],
    [
      0.5262062854683677,
      "flipped_image_135"
    ],
    [
      0.5227760652403194,
      "flipped_image_061"
    ],
    [
      0.4976398159880838,
      "flipped_image_030"
    ],
    [
      0.4897510113257486,
      "flipped_image_031"
    ]
  ],
  "56423": [
    [
      0.5679758167138682,
      "flipped_image_068"
    ],
    [
      0.5622799402303883,
      "image_057"
    ],
    [
      0.5289576612497325,
      "flipped_image_108"
    ],
    [
      0.5265255130318824,
      "flipped_image_076"
    ],
    [
      0.5091642389653342,
      "flipped_image_027"
    ]
  ],
  "56011": [
    [
      0.5502563377063123,
      "flipped_image_027"
    ],
    [
      0.5394213859381894,
      "image_129"
    ],
    [
      0.4985283885619494,
      "flipped_image_041"
    ],
    [
      0.49810145677424,
      "image_027"
    ],
    [
      0.454969825047492,
      "image_033"
    ]
  ],
  "55220": [
    [
      0.49486842774634676,
      "image_099"
    ],
    [
      0.4265561506113517,
      "flipped_image_046"
    ],
    [
      0.4158484072250688,
      "image_140"
    ],
    [
      0.41107681311373934,
      "flipped_image_149"
    ],
    [
      0.4060256105547765,
      "flipped_image_113"
    ]
  ],
  "55744": [
    [
      0.48419544634625833,
      "flipped_image_008"
    ],
    [
      0.4818984528733019,
      "image_033"
    ],
    [
      0.4529162940761606,
      "flipped_image_004"
    ],
    [
      0.4414109313103538,
      "image_146"
    ],
    [
      0.42473555212096015,
      "flipped_image_091"
    ]
  ],
  "55081": [
    [
      0.5086975191084091,
      "flipped_image_039"
    ],
    [
      0.5019114521826252,
      "flipped_image_095"
    ],
    [
      0.4871700178777881,
      "flipped_image_036"
    ],
    [
      0.47580957621929587,
      "image_008"
    ],
    [
      0.420036291581571,
      "flipped_image_069"
    ]
  ],
  "55503": [
    [
      0.5284838191000613,
      "image_089"
    ],
    [
      0.5201919271471858,
      "flipped_image_052"
    ],
    [
      0.5159562079124868,
      "image_014"
    ],
    [
      0.48267330260925995,
      "image_068"
    ],
    [
      0.467658041218866,
      "flipped_image_103"
    ]
  ],
  "56991": [
    [
      0.5254548111848535,
      "flipped_image_052"
    ],
    [
      0.4490627578697574,
      "image_007"
    ],
    [
      0.42662910758506917,
      "image_040"
    ],
    [
      0.41526815962441516,
      "image_096"
    ],
    [
      0.4074347121898861,
      "flipped_image_081"
    ]
  ],
  "56655": [
    [
      0.5224830425071207,
      "image_011"
    ],
    [
      0.5190922064276239,
      "flipped_image_133"
    ],
    [
      0.5161347997954862,
      "image_132"
    ],
    [
      0.511775181205545,
      "flipped_image_139"
    ],
    [
      0.4309561173380377,
      "image_093"
    ]
  ],
  "55488": [
    [
      0.4899371401654933,
      "image_009"
    ],
    [
      0.48621977164902963,
      "flipped_image_025"
    ],
    [
      0.4535595934097464,
      "flipped_image_006"
    ],
    [
      0.44238495542254724,
      "image_136"
    ],
    [
      0.413236440411414,
      "flipped_image_117"
    ]
  ],
  "56771": [
    [
      0.46166771291487335,
      "image_028"
    ],
    [
      0.4594217499200659,
      "image_140"
    ],
    [
      0.43710729757458777,
      "image_139"
    ],
    [
      0.42378536331978145,
      "flipped_image_114"
    ],
    [
      0.42359417913889164,
      "image_125"
    ]
  ],
  "56291": [
    [
      0.4765019405677553,
      "image_089"
    ],
    [
      0.4366873153862114,
      "flipped_image_012"
    ],
    [
      0.4266591047874999,
      "image_057"
    ],
    [
      0.41916526016043043,
      "image_001"
    ],
    [
      0.3823170244418061,
      "image_113"
    ]
  ],
  "55033": [
    [
      0.5506476174430285,
      "flipped_image_041"
    ],
    [
      0.546643168616097,
      "flipped_image_108"
    ],
    [
      0.5212097596945631,
      "image_144"
    ],
    [
      0.47757739952935135,
      "flipped_image_039"
    ],
    [
      0.4503193202083009,
      "flipped_image_139"
    ]
  ],
  "55471": [
    [
      0.5509502900417238,
      "image_106"
    ],
    [
      0.5211286344531023,
      "flipped_image_145"
    ],
    [
      0.5114381828320758,
      "flipped_image_026"
    ],
    [
      0.48981038051845194,
      "image_066"
    ],
    [
      0.48437959768834843,
      "flipped_image_139"
    ]
  ],
  "56791": [
    [
      0.5629702069290008,
      "flipped_image_029"
    ],
    [
      0.5343734933575641,
      "image_104"
    ],
    [
      0.4582869213514639,
      "image_140"
    ],
    [
      0.418029000858527,
      "image_073"
    ],
    [
      0.4115588718608504,
      "flipped_image_077"
    ]
  ],
  "55083": [
    [
      0.5251184736068488,
      "flipped_image_078"
    ],
    [
      0.4931434898611867,
      "image_132"
    ],
    [
      0.4298475329245657,
      "flipped_image_102"
    ],
    [
      0.41564122112744123,
      "flipped_image_111"
    ],
    [
      0.4130732772734187,
      "image_112"
    ]
  ],
  "55579": [
    [
      0.537360439745834,
      "image_002"
    ],
    [
      0.4505907945847756,
      "flipped_image_040"
    ],
    [
      0.4321317800829725,
      "image_146"
    ],
    [
      0.4259323656307181,
      "flipped_image_118"
    ],
    [
      0.4211292328665697,
      "image_118"
    ]
  ],
  "55412": [
    [
      0.5035710017234581,
      "image_092"
    ],
    [
      0.467140655103955,
      "image_016"
    ],
    [
      0.42028549479739974,
      "flipped_image_097"
    ],
    [
      0.4081319802185605,
      "image_080"
    ],
    [
      0.3875210228746557,
      "image_118"
    ]
  ],
  "55908": [
    [
      0.5473195282694913,
      "image_116"
    ],
    [
      0.5296073402826522,
      "flipped_image_051"
    ],
    [
      0.5039959748913454,
      "flipped_image_107"
    ],
    [
      0.43224099532094845,
      "image_114"
    ],
    [
      0.4174097226507477,
      "image_149"
    ]
  ],
  "55085": [
    [
      0.47027248176644976,
      "flipped_image_004"
    ],
    [
      0.4647856796197174,
      "flipped_image_030"
    ],
    [
      0.4151495585244339,
      "image_001"
    ],
    [
      0.4068548141882246,
      "flipped_image_049"
    ],
    [
      0.395644680915311,
      "flipped_image_076"
    ]
  ],
  "56307": [
    [
      0.5260388311691331,
      "image_068"
    ],
    [
      0.4761114668392098,
      "image_056"
    ],
    [
      0.4722253738465773,
      "flipped_image_015"
    ],
    [
      0.4709186696690246,
      "flipped_image_072"
    ],
    [
      0.4642528642508643,
      "flipped_image_071"
    ]
  ],
  "55224": [
    [
      0.5289488272912111,
      "flipped_image_017"
    ],
    [
      0.5287827300432867,
      "flipped_image_027"
    ],
    [
      0.5190401386583523,
      "image_055"
    ],
    [
      0.5148098553327712,
      "flipped_image_119"
    ],
    [
      0.47808382158966467,
      "flipped_image_064"
    ]
  ],
  "55076": [
    [
      0.5510293626111678,
      "image_006"
    ],
    [
      0.4244617813513725,
      "flipped_image_094"
    ],
    [
      0.4190390215182071,
      "flipped_image_088"
    ],
    [
      0.41634604796182617,
      "image_036"
    ],
    [
      0.41119236234834083,
      "flipped_image_138"
    ]
  ],
  "55271": [
    [
      0.5395897334275294,
      "image_011"
    ],
    [
      0.5383722171423588,
      "flipped_image_030"
    ],
    [
      0.5309019804439838,
      "image_103"
    ],
    [
      0.5089148481238868,
      "image_002"
    ],
    [
      0.41408151824032213,
      "image_134"
    ]
  ],
  "55366": [
    [
      0.532964783347346,
      "flipped_image_129"
    ],
    [
      0.4764323388257212,
      "image_028"
    ],
    [
      0.4566664254958128,
      "flipped_image_093"
    ],
    [
      0.4271487531327092,
      "flipped_image_061"
    ],
    [
      0.4153407339745065,
      "flipped_image_092"
    ]
  ],
  "55102": [
    [
      0.5025306352826162,
      "flipped_image_017"
    ],
    [
      0.49766643462559906,
      "flipped_image_093"
    ],
    [
      0.49425775079468237,
      "flipped_image_120"
    ],
    [
      0.3964022441535782,
      "image_117"
    ],
    [
      0.3942976203269971,
      "flipped_image_096"
    ]
  ],
  "55036": [
    [
      0.5064309394379234,
      "flipped_image_034"
    ],
    [
      0.43631235642827304,
      "flipped_image_033"
    ],
    [
      0.413540074385209,
      "flipped_image_005"
    ],
    [
      0.37676149998586955,
      "image_123"
    ],
    [
      0.36447732748368067,
      "flipped_image_098"
    ]
  ],
  "56040": [
    [
      0.8115848576462561,
      "flipped_image_098"
    ],
    [
      0.48937990326938674,
      "image_139"
    ],
    [
      0.48372004650940664,
      "image_071"
    ],
    [
      0.45176146736460154,
      "flipped_image_046"
    ],
    [
      0.4511720803386982,
      "flipped_image_044"
    ]
  ],
  "55051": [
    [
      0.5541912753603856,
      "image_041"
    ],
    [
      0.5409664687394011,
      "flipped_image_030"
    ],
    [
      0.5263651520886706,
      "image_107"
    ],
    [
      0.5040760271992557,
      "flipped_image_028"
    ],
    [
      0.500003383404268,
      "flipped_image_095"
    ]
  ],
  "56059": [
    [
      0.48749362442375177,
      "image_139"
    ],
    [
      0.4818236767553427,
      "flipped_image_071"
    ],
    [
      0.4703207970681907,
      "image_142"
    ],
    [
      0.4398956485545788,
      "image_136"
    ],
    [
      0.3987888232626027,
      "image_125"
    ]
  ],
  "55288": [
    [
      0.5228418781423405,
      "flipped_image_034"
    ],
    [
      0.47179169696168743,
      "flipped_image_033"
    ],
    [
      0.4557322834751606,
      "flipped_image_005"
    ],
    [
      0.4061268782929431,
      "image_123"
    ],
    [
      0.387068869536055,
      "flipped_image_050"
    ]
  ],
  "56430": [
    [
      0.48733973199642555,
      "flipped_image_140"
    ],
    [
      0.46725393678624727,
      "image_097"
    ],
    [
      0.4190705790074278,
      "flipped_image_070"
    ],
    [
      0.39424964496100456,
      "image_147"
    ],
    [
      0.3730273412930407,
      "image_080"
    ]
  ],
  "56886": [
    [
      0.5251115883389424,
      "image_007"
    ],
    [
      0.5222533063842942,
      "image_063"
    ],
    [
      0.5175432731805731,
      "image_057"
    ],
    [
      0.47556965319328376,
      "image_098"
    ],
    [
      0.4673139386557498,
      "flipped_image_128"
    ]
  ],
  "56931": [
    [
      0.4934392988447449,
      "image_132"
    ],
    [
      0.44295851891616767,
      "image_008"
    ],
    [
      0.4310370039197647,
      "flipped_image_146"
    ],
    [
      0.42989173314813195,
      "flipped_image_059"
    ],
    [
      0.4104373839725852,
      "flipped_image_117"
    ]
  ],
  "56286": [
    [
      0.5328458993064046,
      "flipped_image_002"
    ],
    [
      0.4671296808679297,
      "image_127"
    ],
    [
      0.4620967939079819,
      "image_129"
    ],
    [
      0.43930127224866483,
      "flipped_image_108"
    ],
    [
      0.43516767727432343,
      "flipped_image_012"
    ]
  ],
  "56208": [
    [
      0.564322152401836,
      "flipped_image_013"
    ],
    [
      0.5250779901180028,
      "flipped_image_003"
    ],
    [
      0.5042161415975963,
      "image_051"
    ],
    [
      0.5040983885182707,
      "flipped_image_147"
    ],
    [
      0.4806169823622006,
      "flipped_image_120"
    ]
  ],
  "56159": [
    [
      0.5045544675118194,
      "flipped_image_105"
    ],
    [
      0.49363065928762195,
      "image_026"
    ],
    [
      0.47776695848335776,
      "flipped_image_104"
    ],
    [
      0.4260544283480459,
      "image_146"
    ],
    [
      0.42463407942956266,
      "image_078"
    ]
  ],
  "55193": [
    [
      0.5405252391285177,
      "flipped_image_063"
    ],
    [
      0.517447132272666,
      "flipped_image_019"
    ],
    [
      0.499683030582549,
      "image_007"
    ],
    [
      0.4836625856541827,
      "image_014"
    ],
    [
      0.47363567617671654,
      "flipped_image_064"
    ]
  ],
  "55181": [
    [
      0.7848987341961505,
      "flipped_image_110"
    ],
    [
      0.5411197101457695,
      "flipped_image_004"
    ],
    [
      0.4682630381834709,
      "image_136"
    ],
    [
      0.46787819956443294,
      "flipped_image_037"
    ],
    [
      0.43231579042380097,
      "image_146"
    ]
  ],
  "55046": [
    [
      0.5610790048548083,
      "image_090"
    ],
    [
      0.526653769836086,
      "image_144"
    ],
    [
      0.43419528612655045,
      "flipped_image_138"
    ],
    [
      0.4243305273859415,
      "image_098"
    ],
    [
      0.4085727242484929,
      "image_113"
    ]
  ],
  "56002": [
    [
      0.5092638922361352,
      "image_142"
    ],
    [
      0.47625895134305973,
      "image_133"
    ],
    [
      0.46637755047082213,
      "image_058"
    ],
    [
      0.4460229436340568,
      "flipped_image_141"
    ],
    [
      0.4069179550086077,
      "flipped_image_089"
    ]
  ],
  "56937": [
    [
      0.538537544091422,
      "flipped_image_136"
    ],
    [
      0.5383010724259303,
      "image_140"
    ],
    [
      0.5226521717314587,
      "flipped_image_141"
    ],
    [
      0.4907873290650945,
      "flipped_image_024"
    ],
    [
      0.46594008738050974,
      "flipped_image_094"
    ]
  ],
  "55027": [
    [
      0.5452868976011699,
      "flipped_image_032"
    ],
    [
      0.5056559906448489,
      "flipped_image_071"
    ],
    [
      0.4937749256914399,
      "flipped_image_017"
    ],
    [
      0.45461257017829676,
      "image_141"
    ],
    [
      0.43819177317579494,
      "image_118"
    ]
  ],
  "55325": [
    [
      0.49980862398246234,
      "flipped_image_068"
    ],
    [
      0.4721376950960059,
      "flipped_image_027"
    ],
    [
      0.429442896249283,
      "flipped_image_096"
    ],
    [
      0.41549795517613736,
      "image_148"
    ],
    [
      0.4076631046809626,
      "flipped_image_053"
    ]
  ],
  "56122": [
    [
      0.509489355121869,
      "image_030"
    ],
    [
      0.5090944251767154,
      "flipped_image_011"
    ],
    [
      0.4986991083185617,
      "flipped_image_067"
    ],
    [
      0.49657089723714215,
      "image_022"
    ],
    [
      0.4920724013864458,
      "flipped_image_091"
    ]
  ],
  "55231": [
    [
      0.4900158244243854,
      "image_105"
    ],
    [
      0.43029604173833635,
      "image_033"
    ],
    [
      0.4212928172926559,
      "flipped_image_008"
    ],
    [
      0.405912225872867,
      "flipped_image_084"
    ],
    [
      0.3929557117374823,
      "image_130"
    ]
  ],
  "56951": [
    [
      0.5049535039462897,
      "image_035"
    ],
    [
      0.49117794147775556,
      "flipped_image_035"
    ],
    [
      0.48675184589762027,
      "image_008"
    ],
    [
      0.43179456367222785,
      "image_090"
    ],
    [
      0.4191722890909404,
      "flipped_image_059"
    ]
  ],
  "55194": [
    [
      0.5060270022580341,
      "image_035"
    ],
    [
      0.5044682489138758,
      "image_129"
    ],
    [
      0.48414135390539104,
      "flipped_image_128"
    ],
    [
      0.4831618263293333,
      "flipped_image_051"
    ],
    [
      0.47513854131347444,
      "image_032"
    ]
  ],
  "55592": [
    [
      0.7753591763827226,
      "image_108"
    ],
    [
      0.526600054168969,
      "flipped_image_009"
    ],
    [
      0.4910342303148416,
      "image_144"
    ],
    [
      0.4719873202587025,
      "image_061"
    ],
    [
      0.41437757128608577,
      "flipped_image_087"
    ]
  ],
  "55115": [
    [
      0.5296391934430897,
      "image_031"
    ],
    [
      0.42549072228902773,
      "image_007"
    ],
    [
      0.41060261089375333,
      "image_100"
    ],
    [
      0.4002922479306338,
      "image_088"
    ],
    [
      0.38869231043097835,
      "flipped_image_043"
    ]
  ],
  "55161": [
    [
      0.5076022766835702,
      "image_071"
    ],
    [
      0.5024033326140136,
      "flipped_image_033"
    ],
    [
      0.4812754297484925,
      "image_063"
    ],
    [
      0.4714378132321549,
      "flipped_image_073"
    ],
    [
      0.4606046896256695,
      "flipped_image_139"
    ]
  ],
  "55304": [
    [
      0.4599648883967341,
      "image_030"
    ],
    [
      0.39996110337710383,
      "image_023"
    ],
    [
      0.39513580308491103,
      "image_143"
    ],
    [
      0.3842527000984852,
      "image_036"
    ],
    [
      0.37932719161520634,
      "image_067"
    ]
  ],
  "55391": [
    [
      0.8317718838149777,
      "flipped_image_007"
    ],
    [
      0.7745524454363379,
      "image_044"
    ],
    [
      0.5221301797059434,
      "flipped_image_035"
    ],
    [
      0.5036184305571815,
      "flipped_image_143"
    ],
    [
      0.4310584313104993,
      "flipped_image_009"
    ]
  ],
  "56977": [
    [
      0.5587998460805461,
      "image_006"
    ],
    [
      0.5346222473147478,
      "flipped_image_135"
    ],
    [
      0.5101240305038519,
      "flipped_image_141"
    ],
    [
      0.5067619058188187,
      "image_095"
    ],
    [
      0.47489484662451603,
      "flipped_image_076"
    ]
  ],
  "56426": [
    [
      0.5277849845019494,
      "image_133"
    ],
    [
      0.5260079169226982,
      "flipped_image_020"
    ],
    [
      0.508479577202945,
      "image_092"
    ],
    [
      0.4977274551323525,
      "image_004"
    ],
    [
      0.4006976826235427,
      "image_065"
    ]
  ],
  "56074": [
    [
      0.5274037502652522,
      "image_010"
    ],
    [
      0.5225153173673788,
      "flipped_image_052"
    ],
    [
      0.45305941436460767,
      "image_028"
    ],
    [
      0.4315470415599113,
      "image_009"
    ],
    [
      0.409270023249937,
      "image_069"
    ]
  ],
  "55541": [
    [
      0.5159005004966352,
      "flipped_image_007"
    ],
    [
      0.5043145943180197,
      "flipped_image_136"
    ],
    [
      0.49925740690594855,
      "flipped_image_140"
    ],
    [
      0.47764017451600344,
      "flipped_image_040"
    ],
    [
      0.40782560536024576,
      "image_005"
    ]
  ],
  "55502": [
    [
      0.5720628731393063,
      "image_074"
    ],
    [
      0.5160723836053478,
      "flipped_image_094"
    ],
    [
      0.47129379607400074,
      "image_128"
    ],
    [
      0.4565238609837156,
      "image_051"
    ],
    [
      0.4367935024874482,
      "image_138"
    ]
  ],
  "55399": [
    [
      0.5461036304896799,
      "image_063"
    ],
    [
      0.5297994538480727,
      "flipped_image_136"
    ],
    [
      0.5231404298367858,
      "flipped_image_009"
    ],
    [
      0.47779350057275194,
      "flipped_image_064"
    ],
    [
      0.46230099610771935,
      "flipped_image_003"
    ]
  ],
  "55464": [
    [
      0.5228497470096439,
      "image_097"
    ],
    [
      0.5104018947402845,
      "flipped_image_109"
    ],
    [
      0.4853775253656426,
      "image_021"
    ],
    [
      0.48221575608737477,
      "flipped_image_020"
    ],
    [
      0.462353949062488,
      "flipped_image_003"
    ]
  ],
  "56462": [
    [
      0.5210853978385537,
      "flipped_image_056"
    ],
    [
      0.5035038745951743,
      "flipped_image_124"
    ],
    [
      0.451774574972031,
      "image_015"
    ],
    [
      0.42463083266783797,
      "flipped_image_075"
    ],
    [
      0.4127007552805609,
      "flipped_image_086"
    ]
  ],
  "55135": [
    [
      0.5521719950402831,
      "flipped_image_008"
    ],
    [
      0.5495323656664514,
      "image_009"
    ],
    [
      0.5481487226925792,
      "flipped_image_004"
    ],
    [
      0.45352347838339563,
      "image_025"
    ],
    [
      0.43896517018574605,
      "flipped_image_111"
    ]
  ],
  "56998": [
    [
      0.5319859573254715,
      "flipped_image_038"
    ],
    [
      0.5055312454691235,
      "image_138"
    ],
    [
      0.4985360955243567,
      "image_027"
    ],
    [
      0.4283855802187613,
      "image_101"
    ],
    [
      0.41580985911472074,
      "image_126"
    ]
  ],
  "56989": [
    [
      0.8090191151396533,
      "image_081"
    ],
    [
      0.4797834180644337,
      "flipped_image_037"
    ],
    [
      0.42070192540926094,
      "flipped_image_106"
    ],
    [
      0.4100063339428884,
      "image_050"
    ],
    [
      0.4025446095434206,
      "flipped_image_043"
    ]
  ],
  "55025": [
    [
      0.5237172473094366,
      "flipped_image_030"
    ],
    [
      0.5078721477618623,
      "flipped_image_038"
    ],
    [
      0.5054938264402242,
      "flipped_image_046"
    ],
    [
      0.4488345672636063,
      "flipped_image_072"
    ],
    [
      0.4301906441556857,
      "image_039"
    ]
  ],
  "56262": [
    [
      0.5442010613397718,
      "flipped_image_032"
    ],
    [
      0.4977833420731058,
      "flipped_image_025"
    ],
    [
      0.47316531793789535,
      "flipped_image_027"
    ],
    [
      0.4527039110479023,
      "flipped_image_089"
    ],
    [
      0.4269719623042577,
      "flipped_image_141"
    ]
  ],
  "56744": [
    [
      0.5596527780402519,
      "flipped_image_089"
    ],
    [
      0.545831557006355,
      "flipped_image_029"
    ],
    [
      0.5316277279432405,
      "flipped_image_136"
    ],
    [
      0.5140525738750139,
      "flipped_image_018"
    ],
    [
      0.5024709731047015,
      "flipped_image_030"
    ]
  ],
  "55269": [
    [
      0.5234897590402919,
      "flipped_image_015"
    ],
    [
      0.5222831997751032,
      "flipped_image_135"
    ],
    [
      0.5194473508658735,
      "flipped_image_010"
    ],
    [
      0.5162606547446901,
      "flipped_image_006"
    ],
    [
      0.45383069540593257,
      "image_003"
    ]
  ],
  "55872": [
    [
      0.5433257985731864,
      "image_031"
    ],
    [
      0.539733820304385,
      "flipped_image_055"
    ],
    [
      0.5133852017582167,
      "image_060"
    ],
    [
      0.47750318228991956,
      "image_027"
    ],
    [
      0.42389316313762126,
      "flipped_image_077"
    ]
  ],
  "56521": [
    [
      0.8231022688192388,
      "flipped_image_021"
    ],
    [
      0.47298025339114214,
      "image_033"
    ],
    [
      0.39947647817381904,
      "flipped_image_086"
    ],
    [
      0.39771975448077757,
      "image_147"
    ],
    [
      0.3916834278219234,
      "image_048"
    ]
  ],
  "56413": [
    [
      0.5329598168719372,
      "flipped_image_012"
    ],
    [
      0.48378853423585183,
      "flipped_image_002"
    ],
    [
      0.48342299845040776,
      "image_135"
    ],
    [
      0.43233595686762455,
      "image_094"
    ],
    [
      0.4153463211982922,
      "image_097"
    ]
  ],
  "55424": [
    [
      0.7983066766074094,
      "image_133"
    ],
    [
      0.5482321036932156,
      "image_077"
    ],
    [
      0.5365913013484979,
      "image_049"
    ],
    [
      0.5130078364149888,
      "flipped_image_044"
    ],
    [
      0.4261928882765997,
      "image_017"
    ]
  ],
  "55273": [
    [
      0.5162449685742335,
      "flipped_image_003"
    ],
    [
      0.5003261223161042,
      "image_002"
    ],
    [
      0.45409295515456977,
      "image_039"
    ],
    [
      0.44270439092412994,
      "flipped_image_009"
    ],
    [
      0.4239928690246327,
      "image_005"
    ]
  ],
  "55105": [
    [
      0.5407751668396191,
      "image_016"
    ],
    [
      0.5217048733875753,
      "image_131"
    ],
    [
      0.4670329707072413,
      "image_139"
    ],
    [
      0.4325435950411943,
      "image_146"
    ],
    [
      0.4269321907496503,
      "flipped_image_118"
    ]
  ],
  "55943": [
    [
      0.4899002816574983,
      "flipped_image_032"
    ],
    [
      0.4860636145938421,
      "flipped_image_027"
    ],
    [
      0.44769576605851413,
      "flipped_image_014"
    ],
    [
      0.42260515357543527,
      "image_073"
    ],
    [
      0.4050002250431279,
      "image_128"
    ]
  ],
  "56411": [
    [
      0.49152824298076814,
      "flipped_image_030"
    ],
    [
      0.49059580270400766,
      "flipped_image_004"
    ],
    [
      0.47290443590943004,
      "flipped_image_049"
    ],
    [
      0.4333584962541644,
      "flipped_image_119"
    ],
    [
      0.4288050285410445,
      "flipped_image_076"
    ]
  ],
  "55636": [
    [
      0.8300846725932735,
      "image_062"
    ],
    [
      0.5470708110604727,
      "image_032"
    ],
    [
      0.487226287608999,
      "flipped_image_103"
    ],
    [
      0.4791963499885893,
      "flipped_image_124"
    ],
    [
      0.4339334269798778,
      "image_098"
    ]
  ],
  "56245": [
    [
      0.5157712063121641,
      "flipped_image_066"
    ],
    [
      0.47266157181823854,
      "flipped_image_140"
    ],
    [
      0.46750921057683875,
      "flipped_image_139"
    ],
    [
      0.4514123806199726,
      "image_071"
    ],
    [
      0.423759810963275,
      "flipped_image_098"
    ]
  ],
  "55898": [
    [
      0.5356790166785197,
      "flipped_image_041"
    ],
    [
      0.5185189425027211,
      "flipped_image_066"
    ],
    [
      0.44830663805499055,
      "flipped_image_141"
    ],
    [
      0.4236520416622416,
      "flipped_image_148"
    ],
    [
      0.41093200820431924,
      "flipped_image_137"
    ]
  ],
  "55214": [
    [
      0.7590691258975848,
      "flipped_image_046"
    ],
    [
      0.4348420824116736,
      "image_116"
    ],
    [
      0.43315886209065013,
      "image_057"
    ],
    [
      0.42651916552614605,
      "flipped_image_146"
    ],
    [
      0.42366068358703274,
      "flipped_image_107"
    ]
  ],
  "55044": [
    [
      0.5289377806605335,
      "image_030"
    ],
    [
      0.5071720256180499,
      "flipped_image_066"
    ],
    [
      0.47529522950787517,
      "image_092"
    ],
    [
      0.4476373086551444,
      "image_056"
    ],
    [
      0.4292509855591745,
      "image_118"
    ]
  ],
  "56691": [
    [
      0.9235964816376865,
      "image_076"
    ],
    [
      0.5539527828751081,
      "flipped_image_037"
    ],
    [
      0.5471374155740237,
      "flipped_image_057"
    ],
    [
      0.5249262208974446,
      "image_002"
    ],
    [
      0.4776310521934305,
      "image_077"
    ]
  ],
  "55130": [
    [
      0.44727919647366265,
      "image_141"
    ],
    [
      0.4321360796383961,
      "image_082"
    ],
    [
      0.4292866594860564,
      "image_067"
    ],
    [
      0.41814309530118227,
      "image_023"
    ],
    [
      0.40328235732986994,
      "image_013"
    ]
  ],
  "56116": [
    [
      0.5531729770790095,
      "image_092"
    ],
    [
      0.550572833098083,
      "image_090"
    ],
    [
      0.49183154121292566,
      "image_037"
    ],
    [
      0.4727098104230187,
      "image_142"
    ],
    [
      0.47211515553826655,
      "flipped_image_052"
    ]
  ],
  "55174": [
    [
      0.6676898666593095,
      "flipped_image_078"
    ],
    [
      0.41436368749074254,
      "flipped_image_088"
    ],
    [
      0.4093667250244217,
      "flipped_image_148"
    ],
    [
      0.40890556703870706,
      "image_005"
    ],
    [
      0.4074411535864464,
      "image_130"
    ]
  ],
  "55230": [
    [
      0.530841721544675,
      "image_063"
    ],
    [
      0.5188085237492894,
      "image_141"
    ],
    [
      0.4619519087253521,
      "flipped_image_057"
    ],
    [
      0.4444407517919916,
      "image_033"
    ],
    [
      0.39873000353639404,
      "flipped_image_149"
    ]
  ],
  "56008": [
    [
      0.5377113902299636,
      "image_020"
    ],
    [
      0.5124754111377154,
      "flipped_image_030"
    ],
    [
      0.5106692317436031,
      "image_093"
    ],
    [
      0.4844724028094384,
      "flipped_image_095"
    ],
    [
      0.4732187662966343,
      "image_109"
    ]
  ],
  "56265": [
    [
      0.8215874850777666,
      "flipped_image_075"
    ],
    [
      0.5306973082798627,
      "flipped_image_012"
    ],
    [
      0.5186602395194088,
      "image_073"
    ],
    [
      0.498309266540157,
      "flipped_image_124"
    ],
    [
      0.4733517782356924,
      "flipped_image_006"
    ]
  ],
  "56753": [
    [
      0.5356580089441058,
      "flipped_image_135"
    ],
    [
      0.4782477937266712,
      "flipped_image_013"
    ],
    [
      0.41259697165291964,
      "image_066"
    ],
    [
      0.40740102887611757,
      "flipped_image_002"
    ],
    [
      0.39708123038120874,
      "flipped_image_101"
    ]
  ],
  "55418": [
    [
      0.5159128438996929,
      "flipped_image_140"
    ],
    [
      0.5149185869993954,
      "flipped_image_128"
    ],
    [
      0.5073625465078598,
      "image_136"
    ],
    [
      0.4993820127540341,
      "flipped_image_005"
    ],
    [
      0.43161615265481945,
      "image_033"
    ]
  ],
  "55039": [
    [
      0.5194326504711214,
      "flipped_image_104"
    ],
    [
      0.45559542318485874,
      "image_027"
    ],
    [
      0.430732644569849,
      "image_139"
    ],
    [
      0.42798352562919795,
      "flipped_image_099"
    ],
    [
      0.4252566995228007,
      "image_082"
    ]
  ],
  "56447": [
    [
      0.531668379674612,
      "image_012"
    ],
    [
      0.5086862178172906,
      "image_052"
    ],
    [
      0.44480702153609086,
      "flipped_image_072"
    ],
    [
      0.43872291832386734,
      "flipped_image_009"
    ],
    [
      0.3983925968776817,
      "image_125"
    ]
  ],
  "56999": [
    [
      0.5705120704660586,
      "flipped_image_074"
    ],
    [
      0.5240376169890508,
      "flipped_image_041"
    ],
    [
      0.5229999601910276,
      "image_019"
    ],
    [
      0.5081154875093085,
      "flipped_image_064"
    ],
    [
      0.49942548459815367,
      "image_056"
    ]
  ],
  "55428": [
    [
      0.5661220861567814,
      "flipped_image_037"
    ],
    [
      0.5098443124862422,
      "flipped_image_095"
    ],
    [
      0.4910324766188362,
      "flipped_image_090"
    ],
    [
      0.4474448454779441,
      "image_028"
    ],
    [
      0.4425579953639425,
      "flipped_image_064"
    ]
  ],
  "55345": [
    [
      0.575151169858873,
      "flipped_image_037"
    ],
    [
      0.5374635779614265,
      "image_105"
    ],
    [
      0.4858029346646365,
      "flipped_image_140"
    ],
    [
      0.4646306215241607,
      "image_027"
    ],
    [
      0.42571298400987134,
      "flipped_image_023"
    ]
  ],
  "55501": [
    [
      0.5275214960409941,
      "flipped_image_046"
    ],
    [
      0.523115554551743,
      "flipped_image_019"
    ],
    [
      0.4814084722878323,
      "flipped_image_098"
    ],
    [
      0.45542677011299826,
      "image_071"
    ],
    [
      0.45154337746489825,
      "image_139"
    ]
  ],
  "55065": [
    [
      0.5232861987798235,
      "image_057"
    ],
    [
      0.49605727568922015,
      "flipped_image_104"
    ],
    [
      0.4759178463344917,
      "image_033"
    ],
    [
      0.4057441464222188,
      "flipped_image_123"
    ],
    [
      0.39746817019685177,
      "image_064"
    ]
  ],
  "55280": [
    [
      0.509368008320268,
      "image_061"
    ],
    [
      0.4954211423869202,
      "image_010"
    ],
    [
      0.4672208289716403,
      "image_135"
    ],
    [
      0.43260943434620286,
      "image_148"
    ],
    [
      0.4018158138488406,
      "image_047"
    ]
  ],
  "55350": [
    [
      0.5430812914357569,
      "flipped_image_127"
    ],
    [
      0.5321858258240747,
      "flipped_image_031"
    ],
    [
      0.48022505625145845,
      "flipped_image_062"
    ],
    [
      0.47519815250615294,
      "flipped_image_129"
    ],
    [
      0.4501432694249929,
      "image_106"
    ]
  ],
  "56057": [
    [
      0.938144840704814,
      "image_145"
    ],
    [
      0.509140647221364,
      "image_060"
    ],
    [
      0.4952889493099046,
      "flipped_image_052"
    ],
    [
      0.47676807512255437,
      "image_004"
    ],
    [
      0.4709491287962635,
      "image_058"
    ]
  ],
  "55233": [
    [
      0.5388621057212274,
      "flipped_image_116"
    ],
    [
      0.4981733099219152,
      "flipped_image_128"
    ],
    [
      0.41599934830043284,
      "flipped_image_023"
    ],
    [
      0.4122651365570563,
      "flipped_image_134"
    ],
    [
      0.39936296557099477,
      "image_075"
    ]
  ],
  "55186": [
    [
      0.5374740007405693,
      "image_105"
    ],
    [
      0.5198859410073192,
      "flipped_image_145"
    ],
    [
      0.4725931011419,
      "image_106"
    ],
    [
      0.42733683273230155,
      "flipped_image_072"
    ],
    [
      0.42004166996223824,
      "flipped_image_148"
    ]
  ],
  "56375": [
    [
      0.7557416873657646,
      "image_106"
    ],
    [
      0.49293162388548517,
      "image_070"
    ],
    [
      0.4060258707392774,
      "image_088"
    ],
    [
      0.38979417721076337,
      "image_122"
    ],
    [
      0.3878892145524935,
      "image_048"
    ]
  ],
  "55042": [
    [
      0.5207887804303468,
      "image_008"
    ],
    [
      0.5192140302158021,
      "image_139"
    ],
    [
      0.5090228428113407,
      "flipped_image_059"
    ],
    [
      0.4591471598220286,
      "image_135"
    ],
    [
      0.4263566359832097,
      "flipped_image_017"
    ]
  ],
  "55216": [
    [
      0.533086821539574,
      "image_059"
    ],
    [
      0.5115791769493427,
      "image_030"
    ],
    [
      0.45844505489081744,
      "image_073"
    ],
    [
      0.43065166794067467,
      "image_005"
    ],
    [
      0.42249403440677147,
      "image_013"
    ]
  ],
  "55339": [
    [
      0.5306593591352102,
      "flipped_image_104"
    ],
    [
      0.5172359124097048,
      "image_017"
    ],
    [
      0.5032404890284349,
      "image_135"
    ],
    [
      0.4551945505071655,
      "image_139"
    ],
    [
      0.4526408595590828,
      "image_071"
    ]
  ],
  "55329": [
    [
      0.5423723999320264,
      "image_090"
    ],
    [
      0.5140612311737423,
      "flipped_image_071"
    ],
    [
      0.4938529441341709,
      "image_014"
    ],
    [
      0.41586355477561116,
      "image_079"
    ],
    [
      0.41467524882113777,
      "image_081"
    ]
  ],
  "55331": [
    [
      0.5358766051318007,
      "flipped_image_066"
    ],
    [
      0.5040158710616532,
      "flipped_image_041"
    ],
    [
      0.46654996323469416,
      "flipped_image_141"
    ],
    [
      0.45222798848761325,
      "flipped_image_026"
    ],
    [
      0.42830439172434387,
      "image_117"
    ]
  ],
  "56022": [
    [
      0.5257487067471865,
      "flipped_image_063"
    ],
    [
      0.4928302162160728,
      "flipped_image_094"
    ],
    [
      0.4799655881425439,
      "image_010"
    ],
    [
      0.4692824507537511,
      "image_009"
    ],
    [
      0.4677263488568955,
      "image_089"
    ]
  ],
  "55187": [
    [
      0.5447246970349505,
      "flipped_image_022"
    ],
    [
      0.5133257327871148,
      "image_018"
    ],
    [
      0.4764614717472006,
      "image_028"
    ],
    [
      0.4219154129347694,
      "flipped_image_117"
    ],
    [
      0.41591243801770045,
      "image_122"
    ]
  ],
  "55201": [
    [
      0.5496095153756931,
      "image_138"
    ],
    [
      0.4153705024412317,
      "flipped_image_126"
    ],
    [
      0.39412070234240043,
      "flipped_image_100"
    ],
    [
      0.39153371358724215,
      "flipped_image_047"
    ],
    [
      0.38386890883259794,
      "image_081"
    ]
  ],
  "56745": [
    [
      0.5405853402136034,
      "image_138"
    ],
    [
      0.515666817218589,
      "image_127"
    ],
    [
      0.4678061195945443,
      "image_145"
    ],
    [
      0.429947257028789,
      "flipped_image_089"
    ],
    [
      0.42635412208829104,
      "flipped_image_126"
    ]
  ],
  "56079": [
    [
      0.5252255833114263,
      "flipped_image_028"
    ],
    [
      0.4498794848014762,
      "image_078"
    ],
    [
      0.41403837252170667,
      "flipped_image_118"
    ],
    [
      0.400157313053265,
      "flipped_image_084"
    ],
    [
      0.39626002686765843,
      "image_034"
    ]
  ],
  "56017": [
    [
      0.5214932031560419,
      "image_062"
    ],
    [
      0.5074707868119038,
      "flipped_image_049"
    ],
    [
      0.5063412986091101,
      "image_007"
    ],
    [
      0.5028381727561224,
      "flipped_image_007"
    ],
    [
      0.5014988849091929,
      "flipped_image_140"
    ]
  ],
  "55739": [
    [
      0.5240237413522292,
      "image_090"
    ],
    [
      0.5200733266040998,
      "flipped_image_103"
    ],
    [
      0.5130432282096457,
      "image_017"
    ],
    [
      0.4767601013484301,
      "flipped_image_033"
    ],
    [
      0.4747005771560957,
      "image_071"
    ]
  ],
  "56774": [
    [
      0.5348879804646596,
      "image_027"
    ],
    [
      0.49619639150960837,
      "image_127"
    ],
    [
      0.49286799733161435,
      "flipped_image_072"
    ],
    [
      0.47296938218303786,
      "flipped_image_055"
    ],
    [
      0.4703481454288448,
      "flipped_image_004"
    ]
  ],
  "55029": [
    [
      0.5156926214898094,
      "flipped_image_002"
    ],
    [
      0.512676327169381,
      "flipped_image_056"
    ],
    [
      0.48748164538708233,
      "flipped_image_071"
    ],
    [
      0.46763489273725956,
      "flipped_image_106"
    ],
    [
      0.46612647709724364,
      "flipped_image_003"
    ]
  ],
  "55374": [
    [
      0.5465929033220954,
      "image_138"
    ],
    [
      0.47501631945967443,
      "image_063"
    ],
    [
      0.47498976707110285,
      "flipped_image_132"
    ],
    [
      0.47000285877642084,
      "image_031"
    ],
    [
      0.45229803921430894,
      "image_073"
    ]
  ],
  "55945": [
    [
      0.512860854215696,
      "image_097"
    ],
    [
      0.49739711067578296,
      "flipped_image_080"
    ],
    [
      0.4527736621792519,
      "flipped_image_009"
    ],
    [
      0.4400545073379148,
      "image_129"
    ],
    [
      0.41657968251822,
      "image_122"
    ]
  ],
  "56338": [
    [
      0.5004913394309556,
      "image_092"
    ],
    [
      0.47477739872290714,
      "flipped_image_132"
    ],
    [
      0.4591782899930162,
      "image_063"
    ],
    [
      0.44577384612429144,
      "flipped_image_007"
    ],
    [
      0.44087584777836697,
      "flipped_image_067"
    ]
  ],
  "55106": [
    [
      0.506913441990109,
      "flipped_image_059"
    ],
    [
      0.4835203017984224,
      "image_008"
    ],
    [
      0.462901651134087,
      "flipped_image_002"
    ],
    [
      0.46097855929358195,
      "image_104"
    ],
    [
      0.41049889147533775,
      "flipped_image_121"
    ]
  ],
  "55432": [
    [
      0.5464796139537637,
      "image_022"
    ],
    [
      0.5345764622408387,
      "image_062"
    ],
    [
      0.5199701322540742,
      "image_060"
    ],
    [
      0.5048392231667208,
      "image_003"
    ],
    [
      0.48591618277227244,
      "flipped_image_051"
    ]
  ],
  "55478": [
    [
      0.5394813036501983,
      "image_133"
    ],
    [
      0.5265869283408386,
      "flipped_image_074"
    ],
    [
      0.5246811492710246,
      "image_030"
    ],
    [
      0.5245663238598638,
      "flipped_image_124"
    ],
    [
      0.5194090920958835,
      "image_015"
    ]
  ],
  "56186": [
    [
      0.43607523901772227,
      "image_026"
    ],
    [
      0.41790343530237195,
      "image_001"
    ],
    [
      0.41370124427493066,
      "flipped_image_148"
    ],
    [
      0.40885704092215014,
      "image_005"
    ],
    [
      0.4025370629354017,
      "flipped_image_068"
    ]
  ],
  "55127": [
    [
      0.5815821221217905,
      "image_020"
    ],
    [
      0.4682069629866587,
      "image_056"
    ],
    [
      0.45472153750470296,
      "flipped_image_028"
    ],
    [
      0.42550351126955643,
      "flipped_image_001"
    ],
    [
      0.40486148244910536,
      "image_033"
    ]
  ],
  "56993": [
    [
      0.4836321713348938,
      "flipped_image_002"
    ],
    [
      0.4719621347167132,
      "flipped_image_006"
    ],
    [
      0.4638781682017801,
      "image_063"
    ],
    [
      0.4079994208152247,
      "image_094"
    ],
    [
      0.40398631421905984,
      "image_084"
    ]
  ],
  "56275": [
    [
      0.5350911478167034,
      "flipped_image_141"
    ],
    [
      0.5243711964226317,
      "flipped_image_063"
    ],
    [
      0.5182730653635484,
      "image_037"
    ],
    [
      0.4840485071323467,
      "image_029"
    ],
    [
      0.4807988585587857,
      "image_030"
    ]
  ],
  "55479": [
    [
      0.8484498646676182,
      "image_028"
    ],
    [
      0.5380384828626066,
      "flipped_image_061"
    ],
    [
      0.5338848524793712,
      "image_078"
    ],
    [
      0.501708747762342,
      "image_135"
    ],
    [
      0.48279611995531896,
      "flipped_image_095"
    ]
  ],
  "55041": [
    [
      0.5383137207907902,
      "image_089"
    ],
    [
      0.5256566495271282,
      "image_133"
    ],
    [
      0.4357969708831914,
      "image_140"
    ],
    [
      0.41943992509017314,
      "image_100"
    ],
    [
      0.40741208789421746,
      "image_085"
    ]
  ],
  "56966": [
    [
      0.5076813067321685,
      "flipped_image_098"
    ],
    [
      0.5026101432614032,
      "image_007"
    ],
    [
      0.4933323492599785,
      "flipped_image_139"
    ],
    [
      0.4898121144690958,
      "flipped_image_044"
    ],
    [
      0.46365825287444373,
      "flipped_image_011"
    ]
  ],
  "55075": [
    [
      0.5217249895754746,
      "flipped_image_003"
    ],
    [
      0.45736239392671263,
      "flipped_image_027"
    ],
    [
      0.4470655708225557,
      "flipped_image_135"
    ],
    [
      0.44156858713955305,
      "flipped_image_114"
    ],
    [
      0.41089889140754715,
      "image_034"
    ]
  ],
  "56922": [
    [
      0.5311607873980841,
      "image_129"
    ],
    [
      0.5178610337698604,
      "flipped_image_125"
    ],
    [
      0.5073113746003619,
      "flipped_image_140"
    ],
    [
      0.4856463685414334,
      "image_028"
    ],
    [
      0.413083247189345,
      "image_125"
    ]
  ],
  "55394": [
    [
      0.5209084028969485,
      "flipped_image_004"
    ],
    [
      0.4715200301624908,
      "flipped_image_007"
    ],
    [
      0.4610123545765817,
      "flipped_image_063"
    ],
    [
      0.4274564875884427,
      "flipped_image_101"
    ],
    [
      0.41937394001247186,
      "image_040"
    ]
  ],
  "55400": [
    [
      0.5322438972780209,
      "image_089"
    ],
    [
      0.5262524322274061,
      "image_095"
    ],
    [
      0.5067947063804502,
      "image_058"
    ],
    [
      0.5065023295744244,
      "image_110"
    ],
    [
      0.4527855744472275,
      "image_098"
    ]
  ],
  "56885": [
    [
      0.4887780383623518,
      "image_132"
    ],
    [
      0.48730730543096823,
      "flipped_image_132"
    ],
    [
      0.4765379637732868,
      "flipped_image_145"
    ],
    [
      0.45603041171333225,
      "flipped_image_046"
    ],
    [
      0.4506657523699967,
      "flipped_image_008"
    ]
  ],
  "56452": [
    [
      0.541575203372137,
      "image_030"
    ],
    [
      0.5211330817124513,
      "image_133"
    ],
    [
      0.49848439448212867,
      "flipped_image_078"
    ],
    [
      0.41406041975718916,
      "flipped_image_085"
    ],
    [
      0.40195200433206657,
      "image_002"
    ]
  ],
  "55458": [
    [
      0.5150804393562601,
      "image_049"
    ],
    [
      0.4532095447530489,
      "image_073"
    ],
    [
      0.425618575674963,
      "flipped_image_092"
    ],
    [
      0.4148060151374184,
      "image_134"
    ],
    [
      0.40075999038876187,
      "image_067"
    ]
  ],
  "55347": [
    [
      0.5300172933038807,
      "image_136"
    ],
    [
      0.521200942794988,
      "flipped_image_141"
    ],
    [
      0.4541461550939943,
      "image_091"
    ],
    [
      0.408928623501161,
      "image_036"
    ],
    [
      0.4063041705610583,
      "image_134"
    ]
  ],
  "55818": [
    [
      0.5109545707190368,
      "image_105"
    ],
    [
      0.47926669849981335,
      "flipped_image_145"
    ],
    [
      0.445538785958401,
      "flipped_image_005"
    ],
    [
      0.433204191291889,
      "flipped_image_110"
    ],
    [
      0.4118332360401158,
      "flipped_image_126"
    ]
  ],
  "55207": [
    [
      0.5297216818949524,
      "flipped_image_125"
    ],
    [
      0.5288175030409202,
      "flipped_image_056"
    ],
    [
      0.5156864057258661,
      "image_142"
    ],
    [
      0.46779083383573244,
      "image_138"
    ],
    [
      0.4020208041537204,
      "image_100"
    ]
  ],
  "55090": [
    [
      0.5373653980332138,
      "image_004"
    ],
    [
      0.5174988635548056,
      "image_031"
    ],
    [
      0.48642462715312335,
      "image_007"
    ],
    [
      0.47050430532620074,
      "flipped_image_139"
    ],
    [
      0.4582449015245414,
      "image_006"
    ]
  ],
  "55461": [
    [
      0.5172886171140285,
      "image_136"
    ],
    [
      0.5169988525970094,
      "flipped_image_005"
    ],
    [
      0.4449583948805965,
      "flipped_image_145"
    ],
    [
      0.4441768016179675,
      "flipped_image_070"
    ],
    [
      0.4125456448417875,
      "flipped_image_148"
    ]
  ],
  "56997": [
    [
      0.48575400704606636,
      "flipped_image_036"
    ],
    [
      0.3958397224292826,
      "image_137"
    ],
    [
      0.3950094584789305,
      "flipped_image_002"
    ],
    [
      0.38755062937505946,
      "flipped_image_048"
    ],
    [
      0.37599386309513644,
      "flipped_image_042"
    ]
  ],
  "56984": [
    [
      0.5603408169639528,
      "image_063"
    ],
    [
      0.5183226548635058,
      "image_027"
    ],
    [
      0.4339883883736742,
      "image_146"
    ],
    [
      0.41750075249664503,
      "flipped_image_134"
    ],
    [
      0.41052501988745643,
      "image_075"
    ]
  ],
  "56764": [
    [
      0.5395484112145267,
      "flipped_image_055"
    ],
    [
      0.49409823064178876,
      "image_060"
    ],
    [
      0.4475967054151527,
      "image_009"
    ],
    [
      0.41631889285843465,
      "image_124"
    ],
    [
      0.3946499737389205,
      "image_081"
    ]
  ],
  "55237": [
    [
      0.4963684015526169,
      "flipped_image_129"
    ],
    [
      0.47536495319022914,
      "flipped_image_136"
    ],
    [
      0.42929363743172844,
      "image_125"
    ],
    [
      0.42680906631968696,
      "image_101"
    ],
    [
      0.4260850391615058,
      "flipped_image_070"
    ]
  ],
  "56965": [
    [
      0.41131877494340613,
      "image_117"
    ],
    [
      0.4044846521831666,
      "flipped_image_077"
    ],
    [
      0.39383988295830763,
      "flipped_image_126"
    ],
    [
      0.3878441355052006,
      "flipped_image_086"
    ],
    [
      0.38613729191450824,
      "image_083"
    ]
  ],
  "55153": [
    [
      0.5476158207424344,
      "flipped_image_133"
    ],
    [
      0.5292084381060238,
      "flipped_image_034"
    ],
    [
      0.5266079657785117,
      "image_052"
    ],
    [
      0.5210939331643396,
      "flipped_image_032"
    ],
    [
      0.4987992100962071,
      "flipped_image_128"
    ]
  ],
  "55219": [
    [
      0.48870888930631023,
      "flipped_image_080"
    ],
    [
      0.48402687980743486,
      "flipped_image_136"
    ],
    [
      0.48146393229574486,
      "image_041"
    ],
    [
      0.464924643703057,
      "image_071"
    ],
    [
      0.4601552691751934,
      "image_016"
    ]
  ],
  "55430": [
    [
      0.5449123359830859,
      "image_037"
    ],
    [
      0.5412714289922987,
      "flipped_image_067"
    ],
    [
      0.5289574293346051,
      "image_089"
    ],
    [
      0.49099275305399265,
      "flipped_image_007"
    ],
    [
      0.47555852451389197,
      "flipped_image_136"
    ]
  ],
  "55302": [
    [
      0.5552693835111784,
      "flipped_image_017"
    ],
    [
      0.5547919498156317,
      "image_025"
    ],
    [
      0.546909246202516,
      "image_078"
    ],
    [
      0.5392875946756145,
      "flipped_image_038"
    ],
    [
      0.5392687505085975,
      "flipped_image_115"
    ]
  ],
  "55621": [
    [
      0.5483111583193652,
      "flipped_image_057"
    ],
    [
      0.5121688733644622,
      "image_076"
    ],
    [
      0.4730719873146104,
      "flipped_image_092"
    ],
    [
      0.44915669142307546,
      "image_040"
    ],
    [
      0.42970704768100426,
      "image_140"
    ]
  ],
  "55495": [
    [
      0.874769358974632,
      "image_022"
    ],
    [
      0.5297041257063856,
      "flipped_image_129"
    ],
    [
      0.528927127781198,
      "flipped_image_028"
    ],
    [
      0.5033622790447363,
      "image_091"
    ],
    [
      0.4996396707355472,
      "flipped_image_143"
    ]
  ],
  "55059": [
    [
      0.8126733799401791,
      "image_081"
    ],
    [
      0.5479219269758231,
      "flipped_image_037"
    ],
    [
      0.5323834811839356,
      "image_066"
    ],
    [
      0.44184763548541284,
      "flipped_image_046"
    ],
    [
      0.40173799207239724,
      "flipped_image_086"
    ]
  ],
  "56992": [
    [
      0.5447401683278034,
      "image_021"
    ],
    [
      0.5444006823568788,
      "image_142"
    ],
    [
      0.5341240141725342,
      "flipped_image_109"
    ],
    [
      0.4440529588265708,
      "flipped_image_134"
    ],
    [
      0.43083476921931774,
      "flipped_image_077"
    ]
  ],
  "55159": [
    [
      0.5583974110475227,
      "image_011"
    ],
    [
      0.5286486098636906,
      "flipped_image_016"
    ],
    [
      0.4917140037475418,
      "flipped_image_098"
    ],
    [
      0.45393962814308014,
      "image_139"
    ],
    [
      0.42668282008747016,
      "flipped_image_090"
    ]
  ],
  "56043": [
    [
      0.5498331959744346,
      "image_025"
    ],
    [
      0.5052480063675764,
      "flipped_image_131"
    ],
    [
      0.4603375538175163,
      "image_028"
    ],
    [
      0.45218261482022076,
      "flipped_image_073"
    ],
    [
      0.39393045603931987,
      "flipped_image_148"
    ]
  ],
  "55388": [
    [
      0.4252320515104976,
      "image_082"
    ],
    [
      0.419034846141584,
      "image_080"
    ],
    [
      0.3988910823651229,
      "image_143"
    ],
    [
      0.39046197739838306,
      "flipped_image_060"
    ],
    [
      0.3800093722017039,
      "image_046"
    ]
  ],
  "55205": [
    [
      0.5555063106871949,
      "image_136"
    ],
    [
      0.4776246394449237,
      "image_016"
    ],
    [
      0.41962102563349324,
      "flipped_image_100"
    ],
    [
      0.4168105579665009,
      "image_134"
    ],
    [
      0.40554636202174,
      "flipped_image_075"
    ]
  ],
  "56797": [
    [
      0.5388806600278342,
      "image_131"
    ],
    [
      0.4280325930673646,
      "flipped_image_076"
    ],
    [
      0.40696821769942493,
      "image_088"
    ],
    [
      0.4036721848550691,
      "flipped_image_065"
    ],
    [
      0.40255552982232357,
      "flipped_image_079"
    ]
  ],
  "56024": [
    [
      0.5207194714418943,
      "flipped_image_010"
    ],
    [
      0.46368103023860036,
      "flipped_image_002"
    ],
    [
      0.44615950153508976,
      "image_135"
    ],
    [
      0.42434702594640306,
      "flipped_image_065"
    ],
    [
      0.4162777406997101,
      "image_141"
    ]
  ],
  "56568": [
    [
      0.4855300156605894,
      "flipped_image_064"
    ],
    [
      0.46668355935788963,
      "flipped_image_136"
    ],
    [
      0.4653397476423359,
      "image_140"
    ],
    [
      0.45181796762271753,
      "image_058"
    ],
    [
      0.4229744957538101,
      "flipped_image_148"
    ]
  ]
}